ut_cli/__init__.py
ut_cli/__version__.py
ut_cli/aoeq.py
ut_cli/doeq.py
ut_cli/kwargs.py
ut_cli/py.typed
ut_cli/task.py
ut_cli-2.0.2.20251018.dist-info/licenses/LICENSE.txt
ut_cli-2.0.2.20251018.dist-info/METADATA
ut_cli-2.0.2.20251018.dist-info/WHEEL
ut_cli-2.0.2.20251018.dist-info/top_level.txt
ut_cli-2.0.2.20251018.dist-info/RECORD
